mllp_http/__init__.py
mllp_http/http2mllp.py
mllp_http/main.py
mllp_http/mllp.py
mllp_http/mllp2http.py
mllp_http/net.py
mllp_http/version.py
mllp_http-1.1.4.dist-info/LICENSE.txt
mllp_http-1.1.4.dist-info/METADATA
mllp_http-1.1.4.dist-info/WHEEL
mllp_http-1.1.4.dist-info/entry_points.txt
mllp_http-1.1.4.dist-info/top_level.txt
mllp_http-1.1.4.dist-info/RECORD
