Metadata-Version: 2.1
Name: mllp-http
Version: 1.1.4
Summary: Translate between MLLP and HTTP
Home-page: https://github.com/rivethealth/mllp-http
Author: Rivet Health
Author-email: ops@rivethealth.com
License: UNKNOWN
Project-URL: Issues, https://github.com/rivethealth/mllp-http/issues
Platform: UNKNOWN
Classifier: License :: OSI Approved :: MIT License
Classifier: Operating System :: OS Independent
Classifier: Programming Language :: Python
Classifier: Programming Language :: Python :: 3
Requires-Dist: requests
